sustechra_record/__init__.py
sustechra_record/main.py
sustechrawr-1.0.3.dist-info/licenses/LICENSE
sustechrawr-1.0.3.dist-info/METADATA
sustechrawr-1.0.3.dist-info/WHEEL
sustechrawr-1.0.3.dist-info/entry_points.txt
sustechrawr-1.0.3.dist-info/top_level.txt
sustechrawr-1.0.3.dist-info/RECORD
