Metadata-Version: 2.4
Name: sustechRAWR
Version: 1.0.3
Summary: sustech ra work record
License-Expression: Apache-2.0
Requires-Python: >=3.8
License-File: LICENSE
Requires-Dist: get-holiday-cn
Requires-Dist: openpyxl
Requires-Dist: requests
Dynamic: license-file
